libtmux/__about__.py
libtmux/__init__.py
libtmux/_compat.py
libtmux/common.py
libtmux/constants.py
libtmux/exc.py
libtmux/formats.py
libtmux/hooks.py
libtmux/neo.py
libtmux/options.py
libtmux/pane.py
libtmux/py.typed
libtmux/pytest_plugin.py
libtmux/server.py
libtmux/session.py
libtmux/window.py
libtmux/_internal/__init__.py
libtmux/_internal/constants.py
libtmux/_internal/dataclasses.py
libtmux/_internal/query_list.py
libtmux/_internal/sparse_array.py
libtmux/_internal/types.py
libtmux/_vendor/__init__.py
libtmux/_vendor/_structures.py
libtmux/_vendor/version.py
libtmux/test/__init__.py
libtmux/test/constants.py
libtmux/test/environment.py
libtmux/test/random.py
libtmux/test/retry.py
libtmux/test/temporary.py
libtmux-0.52.1.dist-info/METADATA
libtmux-0.52.1.dist-info/WHEEL
libtmux-0.52.1.dist-info/entry_points.txt
libtmux-0.52.1.dist-info/licenses/LICENSE
libtmux-0.52.1.dist-info/RECORD
