Metadata-Version: 2.4
Name: libtmux
Version: 0.52.1
Summary: Typed library that provides an ORM wrapper for tmux, a terminal multiplexer.
Project-URL: Bug Tracker, https://github.com/tmux-python/libtmux/issues
Project-URL: Documentation, https://libtmux.git-pull.com
Project-URL: Repository, https://github.com/tmux-python/libtmux
Project-URL: Changes, https://github.com/tmux-python/libtmux/blob/master/CHANGES
Author-email: Tony Narlock <tony@git-pull.com>
License: MIT
License-File: LICENSE
Keywords: ncurses,session manager,terminal,tmux
Classifier: Development Status :: 5 - Production/Stable
Classifier: Environment :: Web Environment
Classifier: Framework :: Pytest
Classifier: Intended Audience :: Developers
Classifier: License :: OSI Approved :: MIT License
Classifier: Operating System :: MacOS :: MacOS X
Classifier: Operating System :: POSIX
Classifier: Programming Language :: Python
Classifier: Programming Language :: Python :: 3.10
Classifier: Programming Language :: Python :: 3.11
Classifier: Programming Language :: Python :: 3.12
Classifier: Programming Language :: Python :: 3.13
Classifier: Programming Language :: Python :: 3.14
Classifier: Programming Language :: Python :: Implementation :: PyPy
Classifier: Topic :: Software Development :: Libraries :: Python Modules
Classifier: Topic :: System :: Shells
Classifier: Topic :: Utilities
Classifier: Typing :: Typed
Requires-Python: <4.0,>=3.10
